query_chunk/__init__.py
django_query_chunk-0.0.1.dist-info/LICENSE.md
django_query_chunk-0.0.1.dist-info/METADATA
django_query_chunk-0.0.1.dist-info/WHEEL
django_query_chunk-0.0.1.dist-info/top_level.txt
django_query_chunk-0.0.1.dist-info/RECORD
