Metadata-Version: 2.1
Name: django-query-chunk
Version: 0.0.1
Summary: Part QuerySets into small chunks.
Home-page: https://github.com/imbue/django-query-chunk
Author: imbue
Author-email: liamboer@outlook.com
License: UNKNOWN
Platform: UNKNOWN
Classifier: Programming Language :: Python :: 3
Classifier: License :: OSI Approved :: MIT License
Classifier: Operating System :: OS Independent
Requires-Python: >=3.6
